{"timestamp": 1768126698.262691, "data": [{"artists": [{"external_urls": {"spotify": "https://open.spotify.com/artist/3kjuyTCjPG1WMFCiyc5IuB"}, "href": "https://api.spotify.com/v1/artists/3kjuyTCjPG1WMFCiyc5IuB", "id": "3kjuyTCjPG1WMFCiyc5IuB", "name": "Arcade Fire", "type": "artist", "uri": "spotify:artist:3kjuyTCjPG1WMFCiyc5IuB"}, {"external_urls": {"spotify": "https://open.spotify.com/artist/77Rj6PHmQJFb8nbSH62y68"}, "href": "https://api.spotify.com/v1/artists/77Rj6PHmQJFb8nbSH62y68", "id": "77Rj6PHmQJFb8nbSH62y68", "name": "Owen Pallett", "type": "artist", "uri": "spotify:artist:77Rj6PHmQJFb8nbSH62y68"}], "available_markets": ["AR", "AU", "AT", "BE", "BO", "BR", "BG", "CA", "CL", "CO", "CR", "CY", "CZ", "DK", "DO", "DE", "EC", "EE", "SV", "FI", "FR", "GR", "GT", "HN", "HK", "HU", "IS", "IE", "IT", "LV", "LT", "LU", "MY", "MT", "MX", "NL", "NZ", "NI", "NO", "PA", "PY", "PE", "PH", "PL", "PT", "SG", "SK", "ES", "SE", "CH", "TW", "TR", "UY", "US", "GB", "AD", "LI", "MC", "ID", "JP", "TH", "VN", "RO", "IL", "ZA", "SA", "AE", "BH", "QA", "OM", "KW", "EG", "MA", "DZ", "TN", "LB", "JO", "PS", "IN", "BY", "KZ", "MD", "UA", "AL", "BA", "HR", "ME", "MK", "RS", "SI", "KR", "BD", "PK", "LK", "GH", "KE", "NG", "TZ", "UG", "AG", "AM", "BS", "BB", "BZ", "BT", "BW", "BF", "CV", "CW", "DM", "FJ", "GM", "GE", "GD", "GW", "GY", "HT", "JM", "KI", "LS", "LR", "MW", "MV", "ML", "MH", "FM", "NA", "NR", "NE", "PW", "PG", "PR", "WS", "SM", "ST", "SN", "SC", "SL", "SB", "KN", "LC", "VC", "SR", "TL", "TO", "TT", "TV", "VU", "AZ", "BN", "BI", "KH", "CM", "TD", "KM", "GQ", "SZ", "GA", "GN", "KG", "LA", "MO", "MR", "MN", "NP", "RW", "TG", "UZ", "ZW", "BJ", "MG", "MU", "MZ", "AO", "CI", "DJ", "ZM", "CD", "CG", "IQ", "LY", "TJ", "VE", "ET", "XK"], "disc_number": 1, "duration_ms": 194736, "explicit": false, "external_urls": {"spotify": "https://open.spotify.com/track/29CHsXnhpVWvTfsLwqun8I"}, "href": "https://api.spotify.com/v1/tracks/29CHsXnhpVWvTfsLwqun8I", "id": "29CHsXnhpVWvTfsLwqun8I", "name": "Sleepwalker", "preview_url": null, "track_number": 1, "type": "track", "uri": "spotify:track:29CHsXnhpVWvTfsLwqun8I", "is_local": false}, {"artists": [{"external_urls": {"spotify": "https://open.spotify.com/artist/3kjuyTCjPG1WMFCiyc5IuB"}, "href": "https://api.spotify.com/v1/artists/3kjuyTCjPG1WMFCiyc5IuB", "id": "3kjuyTCjPG1WMFCiyc5IuB", "name": "Arcade Fire", "type": "artist", "uri": "spotify:artist:3kjuyTCjPG1WMFCiyc5IuB"}, {"external_urls": {"spotify": "https://open.spotify.com/artist/77Rj6PHmQJFb8nbSH62y68"}, "href": "https://api.spotify.com/v1/artists/77Rj6PHmQJFb8nbSH62y68", "id": "77Rj6PHmQJFb8nbSH62y68", "name": "Owen Pallett", "type": "artist", "uri": "spotify:artist:77Rj6PHmQJFb8nbSH62y68"}], "available_markets": ["AR", "AU", "AT", "BE", "BO", "BR", "BG", "CA", "CL", "CO", "CR", "CY", "CZ", "DK", "DO", "DE", "EC", "EE", "SV", "FI", "FR", "GR", "GT", "HN", "HK", "HU", "IS", "IE", "IT", "LV", "LT", "LU", "MY", "MT", "MX", "NL", "NZ", "NI", "NO", "PA", "PY", "PE", "PH", "PL", "PT", "SG", "SK", "ES", "SE", "CH", "TW", "TR", "UY", "US", "GB", "AD", "LI", "MC", "ID", "JP", "TH", "VN", "RO", "IL", "ZA", "SA", "AE", "BH", "QA", "OM", "KW", "EG", "MA", "DZ", "TN", "LB", "JO", "PS", "IN", "BY", "KZ", "MD", "UA", "AL", "BA", "HR", "ME", "MK", "RS", "SI", "KR", "BD", "PK", "LK", "GH", "KE", "NG", "TZ", "UG", "AG", "AM", "BS", "BB", "BZ", "BT", "BW", "BF", "CV", "CW", "DM", "FJ", "GM", "GE", "GD", "GW", "GY", "HT", "JM", "KI", "LS", "LR", "MW", "MV", "ML", "MH", "FM", "NA", "NR", "NE", "PW", "PG", "PR", "WS", "SM", "ST", "SN", "SC", "SL", "SB", "KN", "LC", "VC", "SR", "TL", "TO", "TT", "TV", "VU", "AZ", "BN", "BI", "KH", "CM", "TD", "KM", "GQ", "SZ", "GA", "GN", "KG", "LA", "MO", "MR", "MN", "NP", "RW", "TG", "UZ", "ZW", "BJ", "MG", "MU", "MZ", "AO", "CI", "DJ", "ZM", "CD", "CG", "IQ", "LY", "TJ", "VE", "ET", "XK"], "disc_number": 1, "duration_ms": 87536, "explicit": false, "external_urls": {"spotify": "https://open.spotify.com/track/4WBTKwO2jebi1Z5NoY8iQu"}, "href": "https://api.spotify.com/v1/tracks/4WBTKwO2jebi1Z5NoY8iQu", "id": "4WBTKwO2jebi1Z5NoY8iQu", "name": "Milk & Honey #1", "preview_url": null, "track_number": 2, "type": "track", "uri": "spotify:track:4WBTKwO2jebi1Z5NoY8iQu", "is_local": false}, {"artists": [{"external_urls": {"spotify": "https://open.spotify.com/artist/3kjuyTCjPG1WMFCiyc5IuB"}, "href": "https://api.spotify.com/v1/artists/3kjuyTCjPG1WMFCiyc5IuB", "id": "3kjuyTCjPG1WMFCiyc5IuB", "name": "Arcade Fire", "type": "artist", "uri": "spotify:artist:3kjuyTCjPG1WMFCiyc5IuB"}, {"external_urls": {"spotify": "https://open.spotify.com/artist/77Rj6PHmQJFb8nbSH62y68"}, "href": "https://api.spotify.com/v1/artists/77Rj6PHmQJFb8nbSH62y68", "id": "77Rj6PHmQJFb8nbSH62y68", "name": "Owen Pallett", "type": "artist", "uri": "spotify:artist:77Rj6PHmQJFb8nbSH62y68"}], "available_markets": ["AR", "AU", "AT", "BE", "BO", "BR", "BG", "CA", "CL", "CO", "CR", "CY", "CZ", "DK", "DO", "DE", "EC", "EE", "SV", "FI", "FR", "GR", "GT", "HN", "HK", "HU", "IS", "IE", "IT", "LV", "LT", "LU", "MY", "MT", "MX", "NL", "NZ", "NI", "NO", "PA", "PY", "PE", "PH", "PL", "PT", "SG", "SK", "ES", "SE", "CH", "TW", "TR", "UY", "US", "GB", "AD", "LI", "MC", "ID", "JP", "TH", "VN", "RO", "IL", "ZA", "SA", "AE", "BH", "QA", "OM", "KW", "EG", "MA", "DZ", "TN", "LB", "JO", "PS", "IN", "BY", "KZ", "MD", "UA", "AL", "BA", "HR", "ME", "MK", "RS", "SI", "KR", "BD", "PK", "LK", "GH", "KE", "NG", "TZ", "UG", "AG", "AM", "BS", "BB", "BZ", "BT", "BW", "BF", "CV", "CW", "DM", "FJ", "GM", "GE", "GD", "GW", "GY", "HT", "JM", "KI", "LS", "LR", "MW", "MV", "ML", "MH", "FM", "NA", "NR", "NE", "PW", "PG", "PR", "WS", "SM", "ST", "SN", "SC", "SL", "SB", "KN", "LC", "VC", "SR", "TL", "TO", "TT", "TV", "VU", "AZ", "BN", "BI", "KH", "CM", "TD", "KM", "GQ", "SZ", "GA", "GN", "KG", "LA", "MO", "MR", "MN", "NP", "RW", "TG", "UZ", "ZW", "BJ", "MG", "MU", "MZ", "AO", "CI", "DJ", "ZM", "CD", "CG", "IQ", "LY", "TJ", "VE", "ET", "XK"], "disc_number": 1, "duration_ms": 205226, "explicit": false, "external_urls": {"spotify": "https://open.spotify.com/track/14G8g61dZX92L7Gr7VFjTO"}, "href": "https://api.spotify.com/v1/tracks/14G8g61dZX92L7Gr7VFjTO", "id": "14G8g61dZX92L7Gr7VFjTO", "name": "Loneliness #3 (Night Talking)", "preview_url": null, "track_number": 3, "type": "track", "uri": "spotify:track:14G8g61dZX92L7Gr7VFjTO", "is_local": false}, {"artists": [{"external_urls": {"spotify": "https://open.spotify.com/artist/3kjuyTCjPG1WMFCiyc5IuB"}, "href": "https://api.spotify.com/v1/artists/3kjuyTCjPG1WMFCiyc5IuB", "id": "3kjuyTCjPG1WMFCiyc5IuB", "name": "Arcade Fire", "type": "artist", "uri": "spotify:artist:3kjuyTCjPG1WMFCiyc5IuB"}, {"external_urls": {"spotify": "https://open.spotify.com/artist/77Rj6PHmQJFb8nbSH62y68"}, "href": "https://api.spotify.com/v1/artists/77Rj6PHmQJFb8nbSH62y68", "id": "77Rj6PHmQJFb8nbSH62y68", "name": "Owen Pallett", "type": "artist", "uri": "spotify:artist:77Rj6PHmQJFb8nbSH62y68"}], "available_markets": ["AR", "AU", "AT", "BE", "BO", "BR", "BG", "CA", "CL", "CO", "CR", "CY", "CZ", "DK", "DO", "DE", "EC", "EE", "SV", "FI", "FR", "GR", "GT", "HN", "HK", "HU", "IS", "IE", "IT", "LV", "LT", "LU", "MY", "MT", "MX", "NL", "NZ", "NI", "NO", "PA", "PY", "PE", "PH", "PL", "PT", "SG", "SK", "ES", "SE", "CH", "TW", "TR", "UY", "US", "GB", "AD", "LI", "MC", "ID", "JP", "TH", "VN", "RO", "IL", "ZA", "SA", "AE", "BH", "QA", "OM", "KW", "EG", "MA", "DZ", "TN", "LB", "JO", "PS", "IN", "BY", "KZ", "MD", "UA", "AL", "BA", "HR", "ME", "MK", "RS", "SI", "KR", "BD", "PK", "LK", "GH", "KE", "NG", "TZ", "UG", "AG", "AM", "BS", "BB", "BZ", "BT", "BW", "BF", "CV", "CW", "DM", "FJ", "GM", "GE", "GD", "GW", "GY", "HT", "JM", "KI", "LS", "LR", "MW", "MV", "ML", "MH", "FM", "NA", "NR", "NE", "PW", "PG", "PR", "WS", "SM", "ST", "SN", "SC", "SL", "SB", "KN", "LC", "VC", "SR", "TL", "TO", "TT", "TV", "VU", "AZ", "BN", "BI", "KH", "CM", "TD", "KM", "GQ", "SZ", "GA", "GN", "KG", "LA", "MO", "MR", "MN", "NP", "RW", "TG", "UZ", "ZW", "BJ", "MG", "MU", "MZ", "AO", "CI", "DJ", "ZM", "CD", "CG", "IQ", "LY", "TJ", "VE", "ET", "XK"], "disc_number": 1, "duration_ms": 194993, "explicit": false, "external_urls": {"spotify": "https://open.spotify.com/track/5OxPPsNISnSHTxDFZfxcAP"}, "href": "https://api.spotify.com/v1/tracks/5OxPPsNISnSHTxDFZfxcAP", "id": "5OxPPsNISnSHTxDFZfxcAP", "name": "Divorce Papers", "preview_url": null, "track_number": 4, "type": "track", "uri": "spotify:track:5OxPPsNISnSHTxDFZfxcAP", "is_local": false}, {"artists": [{"external_urls": {"spotify": "https://open.spotify.com/artist/3kjuyTCjPG1WMFCiyc5IuB"}, "href": "https://api.spotify.com/v1/artists/3kjuyTCjPG1WMFCiyc5IuB", "id": "3kjuyTCjPG1WMFCiyc5IuB", "name": "Arcade Fire", "type": "artist", "uri": "spotify:artist:3kjuyTCjPG1WMFCiyc5IuB"}, {"external_urls": {"spotify": "https://open.spotify.com/artist/77Rj6PHmQJFb8nbSH62y68"}, "href": "https://api.spotify.com/v1/artists/77Rj6PHmQJFb8nbSH62y68", "id": "77Rj6PHmQJFb8nbSH62y68", "name": "Owen Pallett", "type": "artist", "uri": "spotify:artist:77Rj6PHmQJFb8nbSH62y68"}], "available_markets": ["AR", "AU", "AT", "BE", "BO", "BR", "BG", "CA", "CL", "CO", "CR", "CY", "CZ", "DK", "DO", "DE", "EC", "EE", "SV", "FI", "FR", "GR", "GT", "HN", "HK", "HU", "IS", "IE", "IT", "LV", "LT", "LU", "MY", "MT", "MX", "NL", "NZ", "NI", "NO", "PA", "PY", "PE", "PH", "PL", "PT", "SG", "SK", "ES", "SE", "CH", "TW", "TR", "UY", "US", "GB", "AD", "LI", "MC", "ID", "JP", "TH", "VN", "RO", "IL", "ZA", "SA", "AE", "BH", "QA", "OM", "KW", "EG", "MA", "DZ", "TN", "LB", "JO", "PS", "IN", "BY", "KZ", "MD", "UA", "AL", "BA", "HR", "ME", "MK", "RS", "SI", "KR", "BD", "PK", "LK", "GH", "KE", "NG", "TZ", "UG", "AG", "AM", "BS", "BB", "BZ", "BT", "BW", "BF", "CV", "CW", "DM", "FJ", "GM", "GE", "GD", "GW", "GY", "HT", "JM", "KI", "LS", "LR", "MW", "MV", "ML", "MH", "FM", "NA", "NR", "NE", "PW", "PG", "PR", "WS", "SM", "ST", "SN", "SC", "SL", "SB", "KN", "LC", "VC", "SR", "TL", "TO", "TT", "TV", "VU", "AZ", "BN", "BI", "KH", "CM", "TD", "KM", "GQ", "SZ", "GA", "GN", "KG", "LA", "MO", "MR", "MN", "NP", "RW", "TG", "UZ", "ZW", "BJ", "MG", "MU", "MZ", "AO", "CI", "DJ", "ZM", "CD", "CG", "IQ", "LY", "TJ", "VE", "ET", "XK"], "disc_number": 1, "duration_ms": 253901, "explicit": false, "external_urls": {"spotify": "https://open.spotify.com/track/0WjXmnmCCGq5GGlxjD34Zc"}, "href": "https://api.spotify.com/v1/tracks/0WjXmnmCCGq5GGlxjD34Zc", "id": "0WjXmnmCCGq5GGlxjD34Zc", "name": "Morning Talk / Supersymmetry", "preview_url": null, "track_number": 5, "type": "track", "uri": "spotify:track:0WjXmnmCCGq5GGlxjD34Zc", "is_local": false}, {"artists": [{"external_urls": {"spotify": "https://open.spotify.com/artist/3kjuyTCjPG1WMFCiyc5IuB"}, "href": "https://api.spotify.com/v1/artists/3kjuyTCjPG1WMFCiyc5IuB", "id": "3kjuyTCjPG1WMFCiyc5IuB", "name": "Arcade Fire", "type": "artist", "uri": "spotify:artist:3kjuyTCjPG1WMFCiyc5IuB"}, {"external_urls": {"spotify": "https://open.spotify.com/artist/77Rj6PHmQJFb8nbSH62y68"}, "href": "https://api.spotify.com/v1/artists/77Rj6PHmQJFb8nbSH62y68", "id": "77Rj6PHmQJFb8nbSH62y68", "name": "Owen Pallett", "type": "artist", "uri": "spotify:artist:77Rj6PHmQJFb8nbSH62y68"}], "available_markets": ["AR", "AU", "AT", "BE", "BO", "BR", "BG", "CA", "CL", "CO", "CR", "CY", "CZ", "DK", "DO", "DE", "EC", "EE", "SV", "FI", "FR", "GR", "GT", "HN", "HK", "HU", "IS", "IE", "IT", "LV", "LT", "LU", "MY", "MT", "MX", "NL", "NZ", "NI", "NO", "PA", "PY", "PE", "PH", "PL", "PT", "SG", "SK", "ES", "SE", "CH", "TW", "TR", "UY", "US", "GB", "AD", "LI", "MC", "ID", "JP", "TH", "VN", "RO", "IL", "ZA", "SA", "AE", "BH", "QA", "OM", "KW", "EG", "MA", "DZ", "TN", "LB", "JO", "PS", "IN", "BY", "KZ", "MD", "UA", "AL", "BA", "HR", "ME", "MK", "RS", "SI", "KR", "BD", "PK", "LK", "GH", "KE", "NG", "TZ", "UG", "AG", "AM", "BS", "BB", "BZ", "BT", "BW", "BF", "CV", "CW", "DM", "FJ", "GM", "GE", "GD", "GW", "GY", "HT", "JM", "KI", "LS", "LR", "MW", "MV", "ML", "MH", "FM", "NA", "NR", "NE", "PW", "PG", "PR", "WS", "SM", "ST", "SN", "SC", "SL", "SB", "KN", "LC", "VC", "SR", "TL", "TO", "TT", "TV", "VU", "AZ", "BN", "BI", "KH", "CM", "TD", "KM", "GQ", "SZ", "GA", "GN", "KG", "LA", "MO", "MR", "MN", "NP", "RW", "TG", "UZ", "ZW", "BJ", "MG", "MU", "MZ", "AO", "CI", "DJ", "ZM", "CD", "CG", "IQ", "LY", "TJ", "VE", "ET", "XK"], "disc_number": 1, "duration_ms": 218915, "explicit": false, "external_urls": {"spotify": "https://open.spotify.com/track/4vpk2YCWEGEt19zLOxsIs1"}, "href": "https://api.spotify.com/v1/tracks/4vpk2YCWEGEt19zLOxsIs1", "id": "4vpk2YCWEGEt19zLOxsIs1", "name": "Some Other Place", "preview_url": null, "track_number": 6, "type": "track", "uri": "spotify:track:4vpk2YCWEGEt19zLOxsIs1", "is_local": false}, {"artists": [{"external_urls": {"spotify": "https://open.spotify.com/artist/3kjuyTCjPG1WMFCiyc5IuB"}, "href": "https://api.spotify.com/v1/artists/3kjuyTCjPG1WMFCiyc5IuB", "id": "3kjuyTCjPG1WMFCiyc5IuB", "name": "Arcade Fire", "type": "artist", "uri": "spotify:artist:3kjuyTCjPG1WMFCiyc5IuB"}, {"external_urls": {"spotify": "https://open.spotify.com/artist/77Rj6PHmQJFb8nbSH62y68"}, "href": "https://api.spotify.com/v1/artists/77Rj6PHmQJFb8nbSH62y68", "id": "77Rj6PHmQJFb8nbSH62y68", "name": "Owen Pallett", "type": "artist", "uri": "spotify:artist:77Rj6PHmQJFb8nbSH62y68"}], "available_markets": ["AR", "AU", "AT", "BE", "BO", "BR", "BG", "CA", "CL", "CO", "CR", "CY", "CZ", "DK", "DO", "DE", "EC", "EE", "SV", "FI", "FR", "GR", "GT", "HN", "HK", "HU", "IS", "IE", "IT", "LV", "LT", "LU", "MY", "MT", "MX", "NL", "NZ", "NI", "NO", "PA", "PY", "PE", "PH", "PL", "PT", "SG", "SK", "ES", "SE", "CH", "TW", "TR", "UY", "US", "GB", "AD", "LI", "MC", "ID", "JP", "TH", "VN", "RO", "IL", "ZA", "SA", "AE", "BH", "QA", "OM", "KW", "EG", "MA", "DZ", "TN", "LB", "JO", "PS", "IN", "BY", "KZ", "MD", "UA", "AL", "BA", "HR", "ME", "MK", "RS", "SI", "KR", "BD", "PK", "LK", "GH", "KE", "NG", "TZ", "UG", "AG", "AM", "BS", "BB", "BZ", "BT", "BW", "BF", "CV", "CW", "DM", "FJ", "GM", "GE", "GD", "GW", "GY", "HT", "JM", "KI", "LS", "LR", "MW", "MV", "ML", "MH", "FM", "NA", "NR", "NE", "PW", "PG", "PR", "WS", "SM", "ST", "SN", "SC", "SL", "SB", "KN", "LC", "VC", "SR", "TL", "TO", "TT", "TV", "VU", "AZ", "BN", "BI", "KH", "CM", "TD", "KM", "GQ", "SZ", "GA", "GN", "KG", "LA", "MO", "MR", "MN", "NP", "RW", "TG", "UZ", "ZW", "BJ", "MG", "MU", "MZ", "AO", "CI", "DJ", "ZM", "CD", "CG", "IQ", "LY", "TJ", "VE", "ET", "XK"], "disc_number": 1, "duration_ms": 215621, "explicit": false, "external_urls": {"spotify": "https://open.spotify.com/track/606R1WLtU2hPgl0YNfSJ4j"}, "href": "https://api.spotify.com/v1/tracks/606R1WLtU2hPgl0YNfSJ4j", "id": "606R1WLtU2hPgl0YNfSJ4j", "name": "Song on the Beach", "preview_url": null, "track_number": 7, "type": "track", "uri": "spotify:track:606R1WLtU2hPgl0YNfSJ4j", "is_local": false}, {"artists": [{"external_urls": {"spotify": "https://open.spotify.com/artist/3kjuyTCjPG1WMFCiyc5IuB"}, "href": "https://api.spotify.com/v1/artists/3kjuyTCjPG1WMFCiyc5IuB", "id": "3kjuyTCjPG1WMFCiyc5IuB", "name": "Arcade Fire", "type": "artist", "uri": "spotify:artist:3kjuyTCjPG1WMFCiyc5IuB"}, {"external_urls": {"spotify": "https://open.spotify.com/artist/77Rj6PHmQJFb8nbSH62y68"}, "href": "https://api.spotify.com/v1/artists/77Rj6PHmQJFb8nbSH62y68", "id": "77Rj6PHmQJFb8nbSH62y68", "name": "Owen Pallett", "type": "artist", "uri": "spotify:artist:77Rj6PHmQJFb8nbSH62y68"}], "available_markets": ["AR", "AU", "AT", "BE", "BO", "BR", "BG", "CA", "CL", "CO", "CR", "CY", "CZ", "DK", "DO", "DE", "EC", "EE", "SV", "FI", "FR", "GR", "GT", "HN", "HK", "HU", "IS", "IE", "IT", "LV", "LT", "LU", "MY", "MT", "MX", "NL", "NZ", "NI", "NO", "PA", "PY", "PE", "PH", "PL", "PT", "SG", "SK", "ES", "SE", "CH", "TW", "TR", "UY", "US", "GB", "AD", "LI", "MC", "ID", "JP", "TH", "VN", "RO", "IL", "ZA", "SA", "AE", "BH", "QA", "OM", "KW", "EG", "MA", "DZ", "TN", "LB", "JO", "PS", "IN", "BY", "KZ", "MD", "UA", "AL", "BA", "HR", "ME", "MK", "RS", "SI", "KR", "BD", "PK", "LK", "GH", "KE", "NG", "TZ", "UG", "AG", "AM", "BS", "BB", "BZ", "BT", "BW", "BF", "CV", "CW", "DM", "FJ", "GM", "GE", "GD", "GW", "GY", "HT", "JM", "KI", "LS", "LR", "MW", "MV", "ML", "MH", "FM", "NA", "NR", "NE", "PW", "PG", "PR", "WS", "SM", "ST", "SN", "SC", "SL", "SB", "KN", "LC", "VC", "SR", "TL", "TO", "TT", "TV", "VU", "AZ", "BN", "BI", "KH", "CM", "TD", "KM", "GQ", "SZ", "GA", "GN", "KG", "LA", "MO", "MR", "MN", "NP", "RW", "TG", "UZ", "ZW", "BJ", "MG", "MU", "MZ", "AO", "CI", "DJ", "ZM", "CD", "CG", "IQ", "LY", "TJ", "VE", "ET", "XK"], "disc_number": 1, "duration_ms": 59459, "explicit": false, "external_urls": {"spotify": "https://open.spotify.com/track/4QZgUldJxTvOXhSJZxBgTN"}, "href": "https://api.spotify.com/v1/tracks/4QZgUldJxTvOXhSJZxBgTN", "id": "4QZgUldJxTvOXhSJZxBgTN", "name": "Loneliness #4 (Other People's Letters)", "preview_url": null, "track_number": 8, "type": "track", "uri": "spotify:track:4QZgUldJxTvOXhSJZxBgTN", "is_local": false}, {"artists": [{"external_urls": {"spotify": "https://open.spotify.com/artist/3kjuyTCjPG1WMFCiyc5IuB"}, "href": "https://api.spotify.com/v1/artists/3kjuyTCjPG1WMFCiyc5IuB", "id": "3kjuyTCjPG1WMFCiyc5IuB", "name": "Arcade Fire", "type": "artist", "uri": "spotify:artist:3kjuyTCjPG1WMFCiyc5IuB"}, {"external_urls": {"spotify": "https://open.spotify.com/artist/77Rj6PHmQJFb8nbSH62y68"}, "href": "https://api.spotify.com/v1/artists/77Rj6PHmQJFb8nbSH62y68", "id": "77Rj6PHmQJFb8nbSH62y68", "name": "Owen Pallett", "type": "artist", "uri": "spotify:artist:77Rj6PHmQJFb8nbSH62y68"}], "available_markets": ["AR", "AU", "AT", "BE", "BO", "BR", "BG", "CA", "CL", "CO", "CR", "CY", "CZ", "DK", "DO", "DE", "EC", "EE", "SV", "FI", "FR", "GR", "GT", "HN", "HK", "HU", "IS", "IE", "IT", "LV", "LT", "LU", "MY", "MT", "MX", "NL", "NZ", "NI", "NO", "PA", "PY", "PE", "PH", "PL", "PT", "SG", "SK", "ES", "SE", "CH", "TW", "TR", "UY", "US", "GB", "AD", "LI", "MC", "ID", "JP", "TH", "VN", "RO", "IL", "ZA", "SA", "AE", "BH", "QA", "OM", "KW", "EG", "MA", "DZ", "TN", "LB", "JO", "PS", "IN", "BY", "KZ", "MD", "UA", "AL", "BA", "HR", "ME", "MK", "RS", "SI", "KR", "BD", "PK", "LK", "GH", "KE", "NG", "TZ", "UG", "AG", "AM", "BS", "BB", "BZ", "BT", "BW", "BF", "CV", "CW", "DM", "FJ", "GM", "GE", "GD", "GW", "GY", "HT", "JM", "KI", "LS", "LR", "MW", "MV", "ML", "MH", "FM", "NA", "NR", "NE", "PW", "PG", "PR", "WS", "SM", "ST", "SN", "SC", "SL", "SB", "KN", "LC", "VC", "SR", "TL", "TO", "TT", "TV", "VU", "AZ", "BN", "BI", "KH", "CM", "TD", "KM", "GQ", "SZ", "GA", "GN", "KG", "LA", "MO", "MR", "MN", "NP", "RW", "TG", "UZ", "ZW", "BJ", "MG", "MU", "MZ", "AO", "CI", "DJ", "ZM", "CD", "CG", "IQ", "LY", "TJ", "VE", "ET", "XK"], "disc_number": 1, "duration_ms": 140576, "explicit": false, "external_urls": {"spotify": "https://open.spotify.com/track/6Kr2NHIN9c58cpE6j0pqqH"}, "href": "https://api.spotify.com/v1/tracks/6Kr2NHIN9c58cpE6j0pqqH", "id": "6Kr2NHIN9c58cpE6j0pqqH", "name": "Owl", "preview_url": null, "track_number": 9, "type": "track", "uri": "spotify:track:6Kr2NHIN9c58cpE6j0pqqH", "is_local": false}, {"artists": [{"external_urls": {"spotify": "https://open.spotify.com/artist/3kjuyTCjPG1WMFCiyc5IuB"}, "href": "https://api.spotify.com/v1/artists/3kjuyTCjPG1WMFCiyc5IuB", "id": "3kjuyTCjPG1WMFCiyc5IuB", "name": "Arcade Fire", "type": "artist", "uri": "spotify:artist:3kjuyTCjPG1WMFCiyc5IuB"}, {"external_urls": {"spotify": "https://open.spotify.com/artist/77Rj6PHmQJFb8nbSH62y68"}, "href": "https://api.spotify.com/v1/artists/77Rj6PHmQJFb8nbSH62y68", "id": "77Rj6PHmQJFb8nbSH62y68", "name": "Owen Pallett", "type": "artist", "uri": "spotify:artist:77Rj6PHmQJFb8nbSH62y68"}], "available_markets": ["AR", "AU", "AT", "BE", "BO", "BR", "BG", "CA", "CL", "CO", "CR", "CY", "CZ", "DK", "DO", "DE", "EC", "EE", "SV", "FI", "FR", "GR", "GT", "HN", "HK", "HU", "IS", "IE", "IT", "LV", "LT", "LU", "MY", "MT", "MX", "NL", "NZ", "NI", "NO", "PA", "PY", "PE", "PH", "PL", "PT", "SG", "SK", "ES", "SE", "CH", "TW", "TR", "UY", "US", "GB", "AD", "LI", "MC", "ID", "JP", "TH", "VN", "RO", "IL", "ZA", "SA", "AE", "BH", "QA", "OM", "KW", "EG", "MA", "DZ", "TN", "LB", "JO", "PS", "IN", "BY", "KZ", "MD", "UA", "AL", "BA", "HR", "ME", "MK", "RS", "SI", "KR", "BD", "PK", "LK", "GH", "KE", "NG", "TZ", "UG", "AG", "AM", "BS", "BB", "BZ", "BT", "BW", "BF", "CV", "CW", "DM", "FJ", "GM", "GE", "GD", "GW", "GY", "HT", "JM", "KI", "LS", "LR", "MW", "MV", "ML", "MH", "FM", "NA", "NR", "NE", "PW", "PG", "PR", "WS", "SM", "ST", "SN", "SC", "SL", "SB", "KN", "LC", "VC", "SR", "TL", "TO", "TT", "TV", "VU", "AZ", "BN", "BI", "KH", "CM", "TD", "KM", "GQ", "SZ", "GA", "GN", "KG", "LA", "MO", "MR", "MN", "NP", "RW", "TG", "UZ", "ZW", "BJ", "MG", "MU", "MZ", "AO", "CI", "DJ", "ZM", "CD", "CG", "IQ", "LY", "TJ", "VE", "ET", "XK"], "disc_number": 1, "duration_ms": 145803, "explicit": false, "external_urls": {"spotify": "https://open.spotify.com/track/5Sj3F1OEvSz52ehpxTJZlR"}, "href": "https://api.spotify.com/v1/tracks/5Sj3F1OEvSz52ehpxTJZlR", "id": "5Sj3F1OEvSz52ehpxTJZlR", "name": "Photograph", "preview_url": null, "track_number": 10, "type": "track", "uri": "spotify:track:5Sj3F1OEvSz52ehpxTJZlR", "is_local": false}, {"artists": [{"external_urls": {"spotify": "https://open.spotify.com/artist/3kjuyTCjPG1WMFCiyc5IuB"}, "href": "https://api.spotify.com/v1/artists/3kjuyTCjPG1WMFCiyc5IuB", "id": "3kjuyTCjPG1WMFCiyc5IuB", "name": "Arcade Fire", "type": "artist", "uri": "spotify:artist:3kjuyTCjPG1WMFCiyc5IuB"}, {"external_urls": {"spotify": "https://open.spotify.com/artist/77Rj6PHmQJFb8nbSH62y68"}, "href": "https://api.spotify.com/v1/artists/77Rj6PHmQJFb8nbSH62y68", "id": "77Rj6PHmQJFb8nbSH62y68", "name": "Owen Pallett", "type": "artist", "uri": "spotify:artist:77Rj6PHmQJFb8nbSH62y68"}], "available_markets": ["AR", "AU", "AT", "BE", "BO", "BR", "BG", "CA", "CL", "CO", "CR", "CY", "CZ", "DK", "DO", "DE", "EC", "EE", "SV", "FI", "FR", "GR", "GT", "HN", "HK", "HU", "IS", "IE", "IT", "LV", "LT", "LU", "MY", "MT", "MX", "NL", "NZ", "NI", "NO", "PA", "PY", "PE", "PH", "PL", "PT", "SG", "SK", "ES", "SE", "CH", "TW", "TR", "UY", "US", "GB", "AD", "LI", "MC", "ID", "JP", "TH", "VN", "RO", "IL", "ZA", "SA", "AE", "BH", "QA", "OM", "KW", "EG", "MA", "DZ", "TN", "LB", "JO", "PS", "IN", "BY", "KZ", "MD", "UA", "AL", "BA", "HR", "ME", "MK", "RS", "SI", "KR", "BD", "PK", "LK", "GH", "KE", "NG", "TZ", "UG", "AG", "AM", "BS", "BB", "BZ", "BT", "BW", "BF", "CV", "CW", "DM", "FJ", "GM", "GE", "GD", "GW", "GY", "HT", "JM", "KI", "LS", "LR", "MW", "MV", "ML", "MH", "FM", "NA", "NR", "NE", "PW", "PG", "PR", "WS", "SM", "ST", "SN", "SC", "SL", "SB", "KN", "LC", "VC", "SR", "TL", "TO", "TT", "TV", "VU", "AZ", "BN", "BI", "KH", "CM", "TD", "KM", "GQ", "SZ", "GA", "GN", "KG", "LA", "MO", "MR", "MN", "NP", "RW", "TG", "UZ", "ZW", "BJ", "MG", "MU", "MZ", "AO", "CI", "DJ", "ZM", "CD", "CG", "IQ", "LY", "TJ", "VE", "ET", "XK"], "disc_number": 1, "duration_ms": 199128, "explicit": false, "external_urls": {"spotify": "https://open.spotify.com/track/7i6OWt9GW86omn7RW1wtfb"}, "href": "https://api.spotify.com/v1/tracks/7i6OWt9GW86omn7RW1wtfb", "id": "7i6OWt9GW86omn7RW1wtfb", "name": "Milk & Honey #2", "preview_url": null, "track_number": 11, "type": "track", "uri": "spotify:track:7i6OWt9GW86omn7RW1wtfb", "is_local": false}, {"artists": [{"external_urls": {"spotify": "https://open.spotify.com/artist/3kjuyTCjPG1WMFCiyc5IuB"}, "href": "https://api.spotify.com/v1/artists/3kjuyTCjPG1WMFCiyc5IuB", "id": "3kjuyTCjPG1WMFCiyc5IuB", "name": "Arcade Fire", "type": "artist", "uri": "spotify:artist:3kjuyTCjPG1WMFCiyc5IuB"}, {"external_urls": {"spotify": "https://open.spotify.com/artist/77Rj6PHmQJFb8nbSH62y68"}, "href": "https://api.spotify.com/v1/artists/77Rj6PHmQJFb8nbSH62y68", "id": "77Rj6PHmQJFb8nbSH62y68", "name": "Owen Pallett", "type": "artist", "uri": "spotify:artist:77Rj6PHmQJFb8nbSH62y68"}], "available_markets": ["AR", "AU", "AT", "BE", "BO", "BR", "BG", "CA", "CL", "CO", "CR", "CY", "CZ", "DK", "DO", "DE", "EC", "EE", "SV", "FI", "FR", "GR", "GT", "HN", "HK", "HU", "IS", "IE", "IT", "LV", "LT", "LU", "MY", "MT", "MX", "NL", "NZ", "NI", "NO", "PA", "PY", "PE", "PH", "PL", "PT", "SG", "SK", "ES", "SE", "CH", "TW", "TR", "UY", "US", "GB", "AD", "LI", "MC", "ID", "JP", "TH", "VN", "RO", "IL", "ZA", "SA", "AE", "BH", "QA", "OM", "KW", "EG", "MA", "DZ", "TN", "LB", "JO", "PS", "IN", "BY", "KZ", "MD", "UA", "AL", "BA", "HR", "ME", "MK", "RS", "SI", "KR", "BD", "PK", "LK", "GH", "KE", "NG", "TZ", "UG", "AG", "AM", "BS", "BB", "BZ", "BT", "BW", "BF", "CV", "CW", "DM", "FJ", "GM", "GE", "GD", "GW", "GY", "HT", "JM", "KI", "LS", "LR", "MW", "MV", "ML", "MH", "FM", "NA", "NR", "NE", "PW", "PG", "PR", "WS", "SM", "ST", "SN", "SC", "SL", "SB", "KN", "LC", "VC", "SR", "TL", "TO", "TT", "TV", "VU", "AZ", "BN", "BI", "KH", "CM", "TD", "KM", "GQ", "SZ", "GA", "GN", "KG", "LA", "MO", "MR", "MN", "NP", "RW", "TG", "UZ", "ZW", "BJ", "MG", "MU", "MZ", "AO", "CI", "DJ", "ZM", "CD", "CG", "IQ", "LY", "TJ", "VE", "ET", "XK"], "disc_number": 1, "duration_ms": 151367, "explicit": false, "external_urls": {"spotify": "https://open.spotify.com/track/1kltDDXV2gnMfETUdlsL6c"}, "href": "https://api.spotify.com/v1/tracks/1kltDDXV2gnMfETUdlsL6c", "id": "1kltDDXV2gnMfETUdlsL6c", "name": "We're All Leaving", "preview_url": null, "track_number": 12, "type": "track", "uri": "spotify:track:1kltDDXV2gnMfETUdlsL6c", "is_local": false}, {"artists": [{"external_urls": {"spotify": "https://open.spotify.com/artist/3kjuyTCjPG1WMFCiyc5IuB"}, "href": "https://api.spotify.com/v1/artists/3kjuyTCjPG1WMFCiyc5IuB", "id": "3kjuyTCjPG1WMFCiyc5IuB", "name": "Arcade Fire", "type": "artist", "uri": "spotify:artist:3kjuyTCjPG1WMFCiyc5IuB"}, {"external_urls": {"spotify": "https://open.spotify.com/artist/77Rj6PHmQJFb8nbSH62y68"}, "href": "https://api.spotify.com/v1/artists/77Rj6PHmQJFb8nbSH62y68", "id": "77Rj6PHmQJFb8nbSH62y68", "name": "Owen Pallett", "type": "artist", "uri": "spotify:artist:77Rj6PHmQJFb8nbSH62y68"}], "available_markets": ["AR", "AU", "AT", "BE", "BO", "BR", "BG", "CA", "CL", "CO", "CR", "CY", "CZ", "DK", "DO", "DE", "EC", "EE", "SV", "FI", "FR", "GR", "GT", "HN", "HK", "HU", "IS", "IE", "IT", "LV", "LT", "LU", "MY", "MT", "MX", "NL", "NZ", "NI", "NO", "PA", "PY", "PE", "PH", "PL", "PT", "SG", "SK", "ES", "SE", "CH", "TW", "TR", "UY", "US", "GB", "AD", "LI", "MC", "ID", "JP", "TH", "VN", "RO", "IL", "ZA", "SA", "AE", "BH", "QA", "OM", "KW", "EG", "MA", "DZ", "TN", "LB", "JO", "PS", "IN", "BY", "KZ", "MD", "UA", "AL", "BA", "HR", "ME", "MK", "RS", "SI", "KR", "BD", "PK", "LK", "GH", "KE", "NG", "TZ", "UG", "AG", "AM", "BS", "BB", "BZ", "BT", "BW", "BF", "CV", "CW", "DM", "FJ", "GM", "GE", "GD", "GW", "GY", "HT", "JM", "KI", "LS", "LR", "MW", "MV", "ML", "MH", "FM", "NA", "NR", "NE", "PW", "PG", "PR", "WS", "SM", "ST", "SN", "SC", "SL", "SB", "KN", "LC", "VC", "SR", "TL", "TO", "TT", "TV", "VU", "AZ", "BN", "BI", "KH", "CM", "TD", "KM", "GQ", "SZ", "GA", "GN", "KG", "LA", "MO", "MR", "MN", "NP", "RW", "TG", "UZ", "ZW", "BJ", "MG", "MU", "MZ", "AO", "CI", "DJ", "ZM", "CD", "CG", "IQ", "LY", "TJ", "VE", "ET", "XK"], "disc_number": 1, "duration_ms": 339444, "explicit": false, "external_urls": {"spotify": "https://open.spotify.com/track/1F3pzdYyCJlnQoCM9gFzaU"}, "href": "https://api.spotify.com/v1/tracks/1F3pzdYyCJlnQoCM9gFzaU", "id": "1F3pzdYyCJlnQoCM9gFzaU", "name": "Dimensions", "preview_url": null, "track_number": 13, "type": "track", "uri": "spotify:track:1F3pzdYyCJlnQoCM9gFzaU", "is_local": false}]}