{"timestamp": 1768125697.332663, "data": [{"artists": [{"external_urls": {"spotify": "https://open.spotify.com/artist/0YrtvWJMgSdVrk3SfNjTbx"}, "href": "https://api.spotify.com/v1/artists/0YrtvWJMgSdVrk3SfNjTbx", "id": "0YrtvWJMgSdVrk3SfNjTbx", "name": "Death Cab for Cutie", "type": "artist", "uri": "spotify:artist:0YrtvWJMgSdVrk3SfNjTbx"}], "available_markets": ["AR", "AU", "AT", "BE", "BO", "BR", "BG", "CA", "CL", "CO", "CR", "CY", "CZ", "DK", "DO", "DE", "EC", "EE", "SV", "FI", "FR", "GR", "GT", "HN", "HK", "HU", "IS", "IE", "IT", "LV", "LT", "LU", "MY", "MT", "MX", "NL", "NZ", "NI", "NO", "PA", "PY", "PE", "PH", "PL", "PT", "SG", "SK", "ES", "SE", "CH", "TW", "TR", "UY", "US", "GB", "AD", "LI", "MC", "ID", "JP", "TH", "VN", "RO", "IL", "ZA", "SA", "AE", "BH", "QA", "OM", "KW", "EG", "MA", "DZ", "TN", "LB", "JO", "PS", "IN", "KZ", "MD", "UA", "AL", "BA", "HR", "ME", "MK", "RS", "SI", "KR", "BD", "PK", "LK", "GH", "KE", "NG", "TZ", "UG", "AG", "AM", "BS", "BB", "BZ", "BT", "BW", "BF", "CV", "CW", "DM", "FJ", "GM", "GE", "GD", "GW", "GY", "HT", "JM", "KI", "LS", "LR", "MW", "MV", "ML", "MH", "FM", "NA", "NR", "NE", "PW", "PG", "PR", "WS", "SM", "ST", "SN", "SC", "SL", "SB", "KN", "LC", "VC", "SR", "TL", "TO", "TT", "TV", "VU", "AZ", "BN", "BI", "KH", "CM", "TD", "KM", "GQ", "SZ", "GA", "GN", "KG", "LA", "MO", "MR", "MN", "NP", "RW", "TG", "UZ", "ZW", "BJ", "MG", "MU", "MZ", "AO", "CI", "DJ", "ZM", "CD", "CG", "IQ", "LY", "TJ", "VE", "ET", "XK"], "disc_number": 1, "duration_ms": 217269, "explicit": false, "external_urls": {"spotify": "https://open.spotify.com/track/12GEJSBjroCELIxLEnl3mC"}, "href": "https://api.spotify.com/v1/tracks/12GEJSBjroCELIxLEnl3mC", "id": "12GEJSBjroCELIxLEnl3mC", "name": "I Don\u2019t Know How I Survive - Acoustic", "preview_url": null, "track_number": 1, "type": "track", "uri": "spotify:track:12GEJSBjroCELIxLEnl3mC", "is_local": false}, {"artists": [{"external_urls": {"spotify": "https://open.spotify.com/artist/0YrtvWJMgSdVrk3SfNjTbx"}, "href": "https://api.spotify.com/v1/artists/0YrtvWJMgSdVrk3SfNjTbx", "id": "0YrtvWJMgSdVrk3SfNjTbx", "name": "Death Cab for Cutie", "type": "artist", "uri": "spotify:artist:0YrtvWJMgSdVrk3SfNjTbx"}], "available_markets": ["AR", "AU", "AT", "BE", "BO", "BR", "BG", "CA", "CL", "CO", "CR", "CY", "CZ", "DK", "DO", "DE", "EC", "EE", "SV", "FI", "FR", "GR", "GT", "HN", "HK", "HU", "IS", "IE", "IT", "LV", "LT", "LU", "MY", "MT", "MX", "NL", "NZ", "NI", "NO", "PA", "PY", "PE", "PH", "PL", "PT", "SG", "SK", "ES", "SE", "CH", "TW", "TR", "UY", "US", "GB", "AD", "LI", "MC", "ID", "JP", "TH", "VN", "RO", "IL", "ZA", "SA", "AE", "BH", "QA", "OM", "KW", "EG", "MA", "DZ", "TN", "LB", "JO", "PS", "IN", "KZ", "MD", "UA", "AL", "BA", "HR", "ME", "MK", "RS", "SI", "KR", "BD", "PK", "LK", "GH", "KE", "NG", "TZ", "UG", "AG", "AM", "BS", "BB", "BZ", "BT", "BW", "BF", "CV", "CW", "DM", "FJ", "GM", "GE", "GD", "GW", "GY", "HT", "JM", "KI", "LS", "LR", "MW", "MV", "ML", "MH", "FM", "NA", "NR", "NE", "PW", "PG", "PR", "WS", "SM", "ST", "SN", "SC", "SL", "SB", "KN", "LC", "VC", "SR", "TL", "TO", "TT", "TV", "VU", "AZ", "BN", "BI", "KH", "CM", "TD", "KM", "GQ", "SZ", "GA", "GN", "KG", "LA", "MO", "MR", "MN", "NP", "RW", "TG", "UZ", "ZW", "BJ", "MG", "MU", "MZ", "AO", "CI", "DJ", "ZM", "CD", "CG", "IQ", "LY", "TJ", "VE", "ET", "XK"], "disc_number": 1, "duration_ms": 133673, "explicit": false, "external_urls": {"spotify": "https://open.spotify.com/track/4RL12QBrlL78QCPdNvL5SR"}, "href": "https://api.spotify.com/v1/tracks/4RL12QBrlL78QCPdNvL5SR", "id": "4RL12QBrlL78QCPdNvL5SR", "name": "Roman Candles - Acoustic", "preview_url": null, "track_number": 2, "type": "track", "uri": "spotify:track:4RL12QBrlL78QCPdNvL5SR", "is_local": false}, {"artists": [{"external_urls": {"spotify": "https://open.spotify.com/artist/0YrtvWJMgSdVrk3SfNjTbx"}, "href": "https://api.spotify.com/v1/artists/0YrtvWJMgSdVrk3SfNjTbx", "id": "0YrtvWJMgSdVrk3SfNjTbx", "name": "Death Cab for Cutie", "type": "artist", "uri": "spotify:artist:0YrtvWJMgSdVrk3SfNjTbx"}], "available_markets": ["AR", "AU", "AT", "BE", "BO", "BR", "BG", "CA", "CL", "CO", "CR", "CY", "CZ", "DK", "DO", "DE", "EC", "EE", "SV", "FI", "FR", "GR", "GT", "HN", "HK", "HU", "IS", "IE", "IT", "LV", "LT", "LU", "MY", "MT", "MX", "NL", "NZ", "NI", "NO", "PA", "PY", "PE", "PH", "PL", "PT", "SG", "SK", "ES", "SE", "CH", "TW", "TR", "UY", "US", "GB", "AD", "LI", "MC", "ID", "JP", "TH", "VN", "RO", "IL", "ZA", "SA", "AE", "BH", "QA", "OM", "KW", "EG", "MA", "DZ", "TN", "LB", "JO", "PS", "IN", "KZ", "MD", "UA", "AL", "BA", "HR", "ME", "MK", "RS", "SI", "KR", "BD", "PK", "LK", "GH", "KE", "NG", "TZ", "UG", "AG", "AM", "BS", "BB", "BZ", "BT", "BW", "BF", "CV", "CW", "DM", "FJ", "GM", "GE", "GD", "GW", "GY", "HT", "JM", "KI", "LS", "LR", "MW", "MV", "ML", "MH", "FM", "NA", "NR", "NE", "PW", "PG", "PR", "WS", "SM", "ST", "SN", "SC", "SL", "SB", "KN", "LC", "VC", "SR", "TL", "TO", "TT", "TV", "VU", "AZ", "BN", "BI", "KH", "CM", "TD", "KM", "GQ", "SZ", "GA", "GN", "KG", "LA", "MO", "MR", "MN", "NP", "RW", "TG", "UZ", "ZW", "BJ", "MG", "MU", "MZ", "AO", "CI", "DJ", "ZM", "CD", "CG", "IQ", "LY", "TJ", "VE", "ET", "XK"], "disc_number": 1, "duration_ms": 249316, "explicit": false, "external_urls": {"spotify": "https://open.spotify.com/track/0rIq5bmf5owV5LB8atmQTM"}, "href": "https://api.spotify.com/v1/tracks/0rIq5bmf5owV5LB8atmQTM", "id": "0rIq5bmf5owV5LB8atmQTM", "name": "Asphalt Meadows - Acoustic", "preview_url": null, "track_number": 3, "type": "track", "uri": "spotify:track:0rIq5bmf5owV5LB8atmQTM", "is_local": false}, {"artists": [{"external_urls": {"spotify": "https://open.spotify.com/artist/0YrtvWJMgSdVrk3SfNjTbx"}, "href": "https://api.spotify.com/v1/artists/0YrtvWJMgSdVrk3SfNjTbx", "id": "0YrtvWJMgSdVrk3SfNjTbx", "name": "Death Cab for Cutie", "type": "artist", "uri": "spotify:artist:0YrtvWJMgSdVrk3SfNjTbx"}], "available_markets": ["AR", "AU", "AT", "BE", "BO", "BR", "BG", "CA", "CL", "CO", "CR", "CY", "CZ", "DK", "DO", "DE", "EC", "EE", "SV", "FI", "FR", "GR", "GT", "HN", "HK", "HU", "IS", "IE", "IT", "LV", "LT", "LU", "MY", "MT", "MX", "NL", "NZ", "NI", "NO", "PA", "PY", "PE", "PH", "PL", "PT", "SG", "SK", "ES", "SE", "CH", "TW", "TR", "UY", "US", "GB", "AD", "LI", "MC", "ID", "JP", "TH", "VN", "RO", "IL", "ZA", "SA", "AE", "BH", "QA", "OM", "KW", "EG", "MA", "DZ", "TN", "LB", "JO", "PS", "IN", "KZ", "MD", "UA", "AL", "BA", "HR", "ME", "MK", "RS", "SI", "KR", "BD", "PK", "LK", "GH", "KE", "NG", "TZ", "UG", "AG", "AM", "BS", "BB", "BZ", "BT", "BW", "BF", "CV", "CW", "DM", "FJ", "GM", "GE", "GD", "GW", "GY", "HT", "JM", "KI", "LS", "LR", "MW", "MV", "ML", "MH", "FM", "NA", "NR", "NE", "PW", "PG", "PR", "WS", "SM", "ST", "SN", "SC", "SL", "SB", "KN", "LC", "VC", "SR", "TL", "TO", "TT", "TV", "VU", "AZ", "BN", "BI", "KH", "CM", "TD", "KM", "GQ", "SZ", "GA", "GN", "KG", "LA", "MO", "MR", "MN", "NP", "RW", "TG", "UZ", "ZW", "BJ", "MG", "MU", "MZ", "AO", "CI", "DJ", "ZM", "CD", "CG", "IQ", "LY", "TJ", "VE", "ET", "XK"], "disc_number": 1, "duration_ms": 245126, "explicit": false, "external_urls": {"spotify": "https://open.spotify.com/track/44GUcDGoT7ORy4E9rEwU6v"}, "href": "https://api.spotify.com/v1/tracks/44GUcDGoT7ORy4E9rEwU6v", "id": "44GUcDGoT7ORy4E9rEwU6v", "name": "Rand McNally - Acoustic", "preview_url": null, "track_number": 4, "type": "track", "uri": "spotify:track:44GUcDGoT7ORy4E9rEwU6v", "is_local": false}, {"artists": [{"external_urls": {"spotify": "https://open.spotify.com/artist/0YrtvWJMgSdVrk3SfNjTbx"}, "href": "https://api.spotify.com/v1/artists/0YrtvWJMgSdVrk3SfNjTbx", "id": "0YrtvWJMgSdVrk3SfNjTbx", "name": "Death Cab for Cutie", "type": "artist", "uri": "spotify:artist:0YrtvWJMgSdVrk3SfNjTbx"}], "available_markets": ["AR", "AU", "AT", "BE", "BO", "BR", "BG", "CA", "CL", "CO", "CR", "CY", "CZ", "DK", "DO", "DE", "EC", "EE", "SV", "FI", "FR", "GR", "GT", "HN", "HK", "HU", "IS", "IE", "IT", "LV", "LT", "LU", "MY", "MT", "MX", "NL", "NZ", "NI", "NO", "PA", "PY", "PE", "PH", "PL", "PT", "SG", "SK", "ES", "SE", "CH", "TW", "TR", "UY", "US", "GB", "AD", "LI", "MC", "ID", "JP", "TH", "VN", "RO", "IL", "ZA", "SA", "AE", "BH", "QA", "OM", "KW", "EG", "MA", "DZ", "TN", "LB", "JO", "PS", "IN", "KZ", "MD", "UA", "AL", "BA", "HR", "ME", "MK", "RS", "SI", "KR", "BD", "PK", "LK", "GH", "KE", "NG", "TZ", "UG", "AG", "AM", "BS", "BB", "BZ", "BT", "BW", "BF", "CV", "CW", "DM", "FJ", "GM", "GE", "GD", "GW", "GY", "HT", "JM", "KI", "LS", "LR", "MW", "MV", "ML", "MH", "FM", "NA", "NR", "NE", "PW", "PG", "PR", "WS", "SM", "ST", "SN", "SC", "SL", "SB", "KN", "LC", "VC", "SR", "TL", "TO", "TT", "TV", "VU", "AZ", "BN", "BI", "KH", "CM", "TD", "KM", "GQ", "SZ", "GA", "GN", "KG", "LA", "MO", "MR", "MN", "NP", "RW", "TG", "UZ", "ZW", "BJ", "MG", "MU", "MZ", "AO", "CI", "DJ", "ZM", "CD", "CG", "IQ", "LY", "TJ", "VE", "ET", "XK"], "disc_number": 1, "duration_ms": 227425, "explicit": false, "external_urls": {"spotify": "https://open.spotify.com/track/5WQuK76ZFaH7mTIU0loRWs"}, "href": "https://api.spotify.com/v1/tracks/5WQuK76ZFaH7mTIU0loRWs", "id": "5WQuK76ZFaH7mTIU0loRWs", "name": "Here to Forever - Acoustic", "preview_url": null, "track_number": 5, "type": "track", "uri": "spotify:track:5WQuK76ZFaH7mTIU0loRWs", "is_local": false}, {"artists": [{"external_urls": {"spotify": "https://open.spotify.com/artist/0YrtvWJMgSdVrk3SfNjTbx"}, "href": "https://api.spotify.com/v1/artists/0YrtvWJMgSdVrk3SfNjTbx", "id": "0YrtvWJMgSdVrk3SfNjTbx", "name": "Death Cab for Cutie", "type": "artist", "uri": "spotify:artist:0YrtvWJMgSdVrk3SfNjTbx"}], "available_markets": ["AR", "AU", "AT", "BE", "BO", "BR", "BG", "CA", "CL", "CO", "CR", "CY", "CZ", "DK", "DO", "DE", "EC", "EE", "SV", "FI", "FR", "GR", "GT", "HN", "HK", "HU", "IS", "IE", "IT", "LV", "LT", "LU", "MY", "MT", "MX", "NL", "NZ", "NI", "NO", "PA", "PY", "PE", "PH", "PL", "PT", "SG", "SK", "ES", "SE", "CH", "TW", "TR", "UY", "US", "GB", "AD", "LI", "MC", "ID", "JP", "TH", "VN", "RO", "IL", "ZA", "SA", "AE", "BH", "QA", "OM", "KW", "EG", "MA", "DZ", "TN", "LB", "JO", "PS", "IN", "KZ", "MD", "UA", "AL", "BA", "HR", "ME", "MK", "RS", "SI", "KR", "BD", "PK", "LK", "GH", "KE", "NG", "TZ", "UG", "AG", "AM", "BS", "BB", "BZ", "BT", "BW", "BF", "CV", "CW", "DM", "FJ", "GM", "GE", "GD", "GW", "GY", "HT", "JM", "KI", "LS", "LR", "MW", "MV", "ML", "MH", "FM", "NA", "NR", "NE", "PW", "PG", "PR", "WS", "SM", "ST", "SN", "SC", "SL", "SB", "KN", "LC", "VC", "SR", "TL", "TO", "TT", "TV", "VU", "AZ", "BN", "BI", "KH", "CM", "TD", "KM", "GQ", "SZ", "GA", "GN", "KG", "LA", "MO", "MR", "MN", "NP", "RW", "TG", "UZ", "ZW", "BJ", "MG", "MU", "MZ", "AO", "CI", "DJ", "ZM", "CD", "CG", "IQ", "LY", "TJ", "VE", "ET", "XK"], "disc_number": 1, "duration_ms": 305762, "explicit": false, "external_urls": {"spotify": "https://open.spotify.com/track/6Zu6diJy73z6IMOMtYQiSy"}, "href": "https://api.spotify.com/v1/tracks/6Zu6diJy73z6IMOMtYQiSy", "id": "6Zu6diJy73z6IMOMtYQiSy", "name": "Foxglove Through The Clearcut - Acoustic", "preview_url": null, "track_number": 6, "type": "track", "uri": "spotify:track:6Zu6diJy73z6IMOMtYQiSy", "is_local": false}, {"artists": [{"external_urls": {"spotify": "https://open.spotify.com/artist/0YrtvWJMgSdVrk3SfNjTbx"}, "href": "https://api.spotify.com/v1/artists/0YrtvWJMgSdVrk3SfNjTbx", "id": "0YrtvWJMgSdVrk3SfNjTbx", "name": "Death Cab for Cutie", "type": "artist", "uri": "spotify:artist:0YrtvWJMgSdVrk3SfNjTbx"}], "available_markets": ["AR", "AU", "AT", "BE", "BO", "BR", "BG", "CA", "CL", "CO", "CR", "CY", "CZ", "DK", "DO", "DE", "EC", "EE", "SV", "FI", "FR", "GR", "GT", "HN", "HK", "HU", "IS", "IE", "IT", "LV", "LT", "LU", "MY", "MT", "MX", "NL", "NZ", "NI", "NO", "PA", "PY", "PE", "PH", "PL", "PT", "SG", "SK", "ES", "SE", "CH", "TW", "TR", "UY", "US", "GB", "AD", "LI", "MC", "ID", "JP", "TH", "VN", "RO", "IL", "ZA", "SA", "AE", "BH", "QA", "OM", "KW", "EG", "MA", "DZ", "TN", "LB", "JO", "PS", "IN", "KZ", "MD", "UA", "AL", "BA", "HR", "ME", "MK", "RS", "SI", "KR", "BD", "PK", "LK", "GH", "KE", "NG", "TZ", "UG", "AG", "AM", "BS", "BB", "BZ", "BT", "BW", "BF", "CV", "CW", "DM", "FJ", "GM", "GE", "GD", "GW", "GY", "HT", "JM", "KI", "LS", "LR", "MW", "MV", "ML", "MH", "FM", "NA", "NR", "NE", "PW", "PG", "PR", "WS", "SM", "ST", "SN", "SC", "SL", "SB", "KN", "LC", "VC", "SR", "TL", "TO", "TT", "TV", "VU", "AZ", "BN", "BI", "KH", "CM", "TD", "KM", "GQ", "SZ", "GA", "GN", "KG", "LA", "MO", "MR", "MN", "NP", "RW", "TG", "UZ", "ZW", "BJ", "MG", "MU", "MZ", "AO", "CI", "DJ", "ZM", "CD", "CG", "IQ", "LY", "TJ", "VE", "ET", "XK"], "disc_number": 1, "duration_ms": 173155, "explicit": false, "external_urls": {"spotify": "https://open.spotify.com/track/1ayNrehEkJw6tiN1e7OawW"}, "href": "https://api.spotify.com/v1/tracks/1ayNrehEkJw6tiN1e7OawW", "id": "1ayNrehEkJw6tiN1e7OawW", "name": "Pepper - Acoustic", "preview_url": null, "track_number": 7, "type": "track", "uri": "spotify:track:1ayNrehEkJw6tiN1e7OawW", "is_local": false}, {"artists": [{"external_urls": {"spotify": "https://open.spotify.com/artist/0YrtvWJMgSdVrk3SfNjTbx"}, "href": "https://api.spotify.com/v1/artists/0YrtvWJMgSdVrk3SfNjTbx", "id": "0YrtvWJMgSdVrk3SfNjTbx", "name": "Death Cab for Cutie", "type": "artist", "uri": "spotify:artist:0YrtvWJMgSdVrk3SfNjTbx"}], "available_markets": ["AR", "AU", "AT", "BE", "BO", "BR", "BG", "CA", "CL", "CO", "CR", "CY", "CZ", "DK", "DO", "DE", "EC", "EE", "SV", "FI", "FR", "GR", "GT", "HN", "HK", "HU", "IS", "IE", "IT", "LV", "LT", "LU", "MY", "MT", "MX", "NL", "NZ", "NI", "NO", "PA", "PY", "PE", "PH", "PL", "PT", "SG", "SK", "ES", "SE", "CH", "TW", "TR", "UY", "US", "GB", "AD", "LI", "MC", "ID", "JP", "TH", "VN", "RO", "IL", "ZA", "SA", "AE", "BH", "QA", "OM", "KW", "EG", "MA", "DZ", "TN", "LB", "JO", "PS", "IN", "KZ", "MD", "UA", "AL", "BA", "HR", "ME", "MK", "RS", "SI", "KR", "BD", "PK", "LK", "GH", "KE", "NG", "TZ", "UG", "AG", "AM", "BS", "BB", "BZ", "BT", "BW", "BF", "CV", "CW", "DM", "FJ", "GM", "GE", "GD", "GW", "GY", "HT", "JM", "KI", "LS", "LR", "MW", "MV", "ML", "MH", "FM", "NA", "NR", "NE", "PW", "PG", "PR", "WS", "SM", "ST", "SN", "SC", "SL", "SB", "KN", "LC", "VC", "SR", "TL", "TO", "TT", "TV", "VU", "AZ", "BN", "BI", "KH", "CM", "TD", "KM", "GQ", "SZ", "GA", "GN", "KG", "LA", "MO", "MR", "MN", "NP", "RW", "TG", "UZ", "ZW", "BJ", "MG", "MU", "MZ", "AO", "CI", "DJ", "ZM", "CD", "CG", "IQ", "LY", "TJ", "VE", "ET", "XK"], "disc_number": 1, "duration_ms": 167022, "explicit": false, "external_urls": {"spotify": "https://open.spotify.com/track/53LueuvPEMgEZLzVfssBwJ"}, "href": "https://api.spotify.com/v1/tracks/53LueuvPEMgEZLzVfssBwJ", "id": "53LueuvPEMgEZLzVfssBwJ", "name": "I Miss Strangers - Acoustic", "preview_url": null, "track_number": 8, "type": "track", "uri": "spotify:track:53LueuvPEMgEZLzVfssBwJ", "is_local": false}, {"artists": [{"external_urls": {"spotify": "https://open.spotify.com/artist/0YrtvWJMgSdVrk3SfNjTbx"}, "href": "https://api.spotify.com/v1/artists/0YrtvWJMgSdVrk3SfNjTbx", "id": "0YrtvWJMgSdVrk3SfNjTbx", "name": "Death Cab for Cutie", "type": "artist", "uri": "spotify:artist:0YrtvWJMgSdVrk3SfNjTbx"}], "available_markets": ["AR", "AU", "AT", "BE", "BO", "BR", "BG", "CA", "CL", "CO", "CR", "CY", "CZ", "DK", "DO", "DE", "EC", "EE", "SV", "FI", "FR", "GR", "GT", "HN", "HK", "HU", "IS", "IE", "IT", "LV", "LT", "LU", "MY", "MT", "MX", "NL", "NZ", "NI", "NO", "PA", "PY", "PE", "PH", "PL", "PT", "SG", "SK", "ES", "SE", "CH", "TW", "TR", "UY", "US", "GB", "AD", "LI", "MC", "ID", "JP", "TH", "VN", "RO", "IL", "ZA", "SA", "AE", "BH", "QA", "OM", "KW", "EG", "MA", "DZ", "TN", "LB", "JO", "PS", "IN", "KZ", "MD", "UA", "AL", "BA", "HR", "ME", "MK", "RS", "SI", "KR", "BD", "PK", "LK", "GH", "KE", "NG", "TZ", "UG", "AG", "AM", "BS", "BB", "BZ", "BT", "BW", "BF", "CV", "CW", "DM", "FJ", "GM", "GE", "GD", "GW", "GY", "HT", "JM", "KI", "LS", "LR", "MW", "MV", "ML", "MH", "FM", "NA", "NR", "NE", "PW", "PG", "PR", "WS", "SM", "ST", "SN", "SC", "SL", "SB", "KN", "LC", "VC", "SR", "TL", "TO", "TT", "TV", "VU", "AZ", "BN", "BI", "KH", "CM", "TD", "KM", "GQ", "SZ", "GA", "GN", "KG", "LA", "MO", "MR", "MN", "NP", "RW", "TG", "UZ", "ZW", "BJ", "MG", "MU", "MZ", "AO", "CI", "DJ", "ZM", "CD", "CG", "IQ", "LY", "TJ", "VE", "ET", "XK"], "disc_number": 1, "duration_ms": 219818, "explicit": false, "external_urls": {"spotify": "https://open.spotify.com/track/6Rzj9CRw6c03edi1Pu7kpG"}, "href": "https://api.spotify.com/v1/tracks/6Rzj9CRw6c03edi1Pu7kpG", "id": "6Rzj9CRw6c03edi1Pu7kpG", "name": "Wheat Like Waves - Acoustic", "preview_url": null, "track_number": 9, "type": "track", "uri": "spotify:track:6Rzj9CRw6c03edi1Pu7kpG", "is_local": false}, {"artists": [{"external_urls": {"spotify": "https://open.spotify.com/artist/0YrtvWJMgSdVrk3SfNjTbx"}, "href": "https://api.spotify.com/v1/artists/0YrtvWJMgSdVrk3SfNjTbx", "id": "0YrtvWJMgSdVrk3SfNjTbx", "name": "Death Cab for Cutie", "type": "artist", "uri": "spotify:artist:0YrtvWJMgSdVrk3SfNjTbx"}], "available_markets": ["AR", "AU", "AT", "BE", "BO", "BR", "BG", "CA", "CL", "CO", "CR", "CY", "CZ", "DK", "DO", "DE", "EC", "EE", "SV", "FI", "FR", "GR", "GT", "HN", "HK", "HU", "IS", "IE", "IT", "LV", "LT", "LU", "MY", "MT", "MX", "NL", "NZ", "NI", "NO", "PA", "PY", "PE", "PH", "PL", "PT", "SG", "SK", "ES", "SE", "CH", "TW", "TR", "UY", "US", "GB", "AD", "LI", "MC", "ID", "JP", "TH", "VN", "RO", "IL", "ZA", "SA", "AE", "BH", "QA", "OM", "KW", "EG", "MA", "DZ", "TN", "LB", "JO", "PS", "IN", "KZ", "MD", "UA", "AL", "BA", "HR", "ME", "MK", "RS", "SI", "KR", "BD", "PK", "LK", "GH", "KE", "NG", "TZ", "UG", "AG", "AM", "BS", "BB", "BZ", "BT", "BW", "BF", "CV", "CW", "DM", "FJ", "GM", "GE", "GD", "GW", "GY", "HT", "JM", "KI", "LS", "LR", "MW", "MV", "ML", "MH", "FM", "NA", "NR", "NE", "PW", "PG", "PR", "WS", "SM", "ST", "SN", "SC", "SL", "SB", "KN", "LC", "VC", "SR", "TL", "TO", "TT", "TV", "VU", "AZ", "BN", "BI", "KH", "CM", "TD", "KM", "GQ", "SZ", "GA", "GN", "KG", "LA", "MO", "MR", "MN", "NP", "RW", "TG", "UZ", "ZW", "BJ", "MG", "MU", "MZ", "AO", "CI", "DJ", "ZM", "CD", "CG", "IQ", "LY", "TJ", "VE", "ET", "XK"], "disc_number": 1, "duration_ms": 213971, "explicit": false, "external_urls": {"spotify": "https://open.spotify.com/track/32fD7AAlnBgUJf09gpM3HN"}, "href": "https://api.spotify.com/v1/tracks/32fD7AAlnBgUJf09gpM3HN", "id": "32fD7AAlnBgUJf09gpM3HN", "name": "Fragments From the Decade - Acoustic", "preview_url": null, "track_number": 10, "type": "track", "uri": "spotify:track:32fD7AAlnBgUJf09gpM3HN", "is_local": false}, {"artists": [{"external_urls": {"spotify": "https://open.spotify.com/artist/0YrtvWJMgSdVrk3SfNjTbx"}, "href": "https://api.spotify.com/v1/artists/0YrtvWJMgSdVrk3SfNjTbx", "id": "0YrtvWJMgSdVrk3SfNjTbx", "name": "Death Cab for Cutie", "type": "artist", "uri": "spotify:artist:0YrtvWJMgSdVrk3SfNjTbx"}], "available_markets": ["AR", "AU", "AT", "BE", "BO", "BR", "BG", "CA", "CL", "CO", "CR", "CY", "CZ", "DK", "DO", "DE", "EC", "EE", "SV", "FI", "FR", "GR", "GT", "HN", "HK", "HU", "IS", "IE", "IT", "LV", "LT", "LU", "MY", "MT", "MX", "NL", "NZ", "NI", "NO", "PA", "PY", "PE", "PH", "PL", "PT", "SG", "SK", "ES", "SE", "CH", "TW", "TR", "UY", "US", "GB", "AD", "LI", "MC", "ID", "JP", "TH", "VN", "RO", "IL", "ZA", "SA", "AE", "BH", "QA", "OM", "KW", "EG", "MA", "DZ", "TN", "LB", "JO", "PS", "IN", "KZ", "MD", "UA", "AL", "BA", "HR", "ME", "MK", "RS", "SI", "KR", "BD", "PK", "LK", "GH", "KE", "NG", "TZ", "UG", "AG", "AM", "BS", "BB", "BZ", "BT", "BW", "BF", "CV", "CW", "DM", "FJ", "GM", "GE", "GD", "GW", "GY", "HT", "JM", "KI", "LS", "LR", "MW", "MV", "ML", "MH", "FM", "NA", "NR", "NE", "PW", "PG", "PR", "WS", "SM", "ST", "SN", "SC", "SL", "SB", "KN", "LC", "VC", "SR", "TL", "TO", "TT", "TV", "VU", "AZ", "BN", "BI", "KH", "CM", "TD", "KM", "GQ", "SZ", "GA", "GN", "KG", "LA", "MO", "MR", "MN", "NP", "RW", "TG", "UZ", "ZW", "BJ", "MG", "MU", "MZ", "AO", "CI", "DJ", "ZM", "CD", "CG", "IQ", "LY", "TJ", "VE", "ET", "XK"], "disc_number": 1, "duration_ms": 120532, "explicit": false, "external_urls": {"spotify": "https://open.spotify.com/track/5157ZEu0cK7k6uULpJ0KNU"}, "href": "https://api.spotify.com/v1/tracks/5157ZEu0cK7k6uULpJ0KNU", "id": "5157ZEu0cK7k6uULpJ0KNU", "name": "I\u2019ll Never Give Up On You - Acoustic", "preview_url": null, "track_number": 11, "type": "track", "uri": "spotify:track:5157ZEu0cK7k6uULpJ0KNU", "is_local": false}, {"artists": [{"external_urls": {"spotify": "https://open.spotify.com/artist/0YrtvWJMgSdVrk3SfNjTbx"}, "href": "https://api.spotify.com/v1/artists/0YrtvWJMgSdVrk3SfNjTbx", "id": "0YrtvWJMgSdVrk3SfNjTbx", "name": "Death Cab for Cutie", "type": "artist", "uri": "spotify:artist:0YrtvWJMgSdVrk3SfNjTbx"}], "available_markets": ["AR", "AU", "AT", "BE", "BO", "BR", "BG", "CA", "CL", "CO", "CR", "CY", "CZ", "DK", "DO", "DE", "EC", "EE", "SV", "FI", "FR", "GR", "GT", "HN", "HK", "HU", "IS", "IE", "IT", "LV", "LT", "LU", "MY", "MT", "MX", "NL", "NZ", "NI", "NO", "PA", "PY", "PE", "PH", "PL", "PT", "SG", "SK", "ES", "SE", "CH", "TW", "TR", "UY", "US", "GB", "AD", "LI", "MC", "ID", "JP", "TH", "VN", "RO", "IL", "ZA", "SA", "AE", "BH", "QA", "OM", "KW", "EG", "MA", "DZ", "TN", "LB", "JO", "PS", "IN", "KZ", "MD", "UA", "AL", "BA", "HR", "ME", "MK", "RS", "SI", "KR", "BD", "PK", "LK", "GH", "KE", "NG", "TZ", "UG", "AG", "AM", "BS", "BB", "BZ", "BT", "BW", "BF", "CV", "CW", "DM", "FJ", "GM", "GE", "GD", "GW", "GY", "HT", "JM", "KI", "LS", "LR", "MW", "MV", "ML", "MH", "FM", "NA", "NR", "NE", "PW", "PG", "PR", "WS", "SM", "ST", "SN", "SC", "SL", "SB", "KN", "LC", "VC", "SR", "TL", "TO", "TT", "TV", "VU", "AZ", "BN", "BI", "KH", "CM", "TD", "KM", "GQ", "SZ", "GA", "GN", "KG", "LA", "MO", "MR", "MN", "NP", "RW", "TG", "UZ", "ZW", "BJ", "MG", "MU", "MZ", "AO", "CI", "DJ", "ZM", "CD", "CG", "IQ", "LY", "TJ", "VE", "ET", "XK"], "disc_number": 1, "duration_ms": 213646, "explicit": false, "external_urls": {"spotify": "https://open.spotify.com/track/09Sdwo4xV2u3X3qexTGAUr"}, "href": "https://api.spotify.com/v1/tracks/09Sdwo4xV2u3X3qexTGAUr", "id": "09Sdwo4xV2u3X3qexTGAUr", "name": "The Plan", "preview_url": null, "track_number": 12, "type": "track", "uri": "spotify:track:09Sdwo4xV2u3X3qexTGAUr", "is_local": false}]}